CHANGES.md
LICENSE
MANIFEST.in
README.md
setup.py
dj_tiny_api/__init__.py
dj_tiny_api/test.py
dj_tiny_api/v2.py
dj_tiny_api.egg-info/PKG-INFO
dj_tiny_api.egg-info/SOURCES.txt
dj_tiny_api.egg-info/dependency_links.txt
dj_tiny_api.egg-info/requires.txt
dj_tiny_api.egg-info/top_level.txt